agci.py
agci-0.0.2.dist-info/METADATA
agci-0.0.2.dist-info/WHEEL
agci-0.0.2.dist-info/entry_points.txt
agci-0.0.2.dist-info/top_level.txt
agci-0.0.2.dist-info/RECORD
