Metadata-Version: 2.1
Name: agci
Version: 0.0.2
Summary: how to debut a PyPI for chemistry
Home-page: https://github.com/y-takefuji/agci
Author: yoshiyasu takefuji
Author-email: takefuji@keio.jp
License: UNKNOWN
Project-URL: Bug Tracker, https://github.com/y-takefuji/agci
Platform: UNKNOWN
Classifier: Programming Language :: Python :: 3
Classifier: License :: OSI Approved :: MIT License
Classifier: Operating System :: OS Independent
Requires-Python: >=3.8
